LICENSE
MANIFEST.in
README.md
setup.py
gpt_2_simple/__init__.py
gpt_2_simple/gpt_2.py
gpt_2_simple.egg-info/PKG-INFO
gpt_2_simple.egg-info/SOURCES.txt
gpt_2_simple.egg-info/dependency_links.txt
gpt_2_simple.egg-info/entry_points.txt
gpt_2_simple.egg-info/requires.txt
gpt_2_simple.egg-info/top_level.txt
gpt_2_simple/src/__init__.py
gpt_2_simple/src/accumulate.py
gpt_2_simple/src/encoder.py
gpt_2_simple/src/load_dataset.py
gpt_2_simple/src/memory_saving_gradients.py
gpt_2_simple/src/model.py
gpt_2_simple/src/sample.py