Metadata-Version: 2.1
Name: gpt-2-simple
Version: 0.8.1
Summary: Python package to easily retrain OpenAI's GPT-2 text-generating model on new texts.
Home-page: https://github.com/minimaxir/gpt-2-simple
Author: Max Woolf
Author-email: max@minimaxir.com
License: MIT
Keywords: deep learning,tensorflow,text generation
Platform: UNKNOWN
Requires-Python: >=3.6
